{"v":"5.1.18","fr":30,"ip":0,"op":30,"w":56,"h":56,"nm":"点赞信息流全屏","ddd":0,"assets":[],"layers":[{"ddd":0,"ind":1,"ty":4,"nm":"“moment_tool_like_sel”轮廓","sr":1,"ks":{"o":{"a":0,"k":100,"ix":11},"r":{"a":0,"k":0,"ix":10},"p":{"a":0,"k":[28,28,0],"ix":2},"a":{"a":0,"k":[16,16,0],"ix":1},"s":{"a":0,"k":[100,100,100],"ix":6}},"ao":0,"shapes":[{"ty":"gr","it":[{"ind":0,"ty":"sh","ix":1,"ks":{"a":0,"k":{"i":[[0.91,-0.563],[0.422,-0.428],[0.46,0.286],[1.233,0],[0.329,-0.033],[0.947,-1.021],[0.144,-1.793],[0,0],[-1.62,-1.806],[-3.73,-2.653],[0,0],[-0.256,0.115],[0,0],[0,0],[0,0],[-1.504,1.683],[-0.144,1.92],[0,0],[0,0],[1.078,1.153],[1.272,0.13],[0.349,0]],"o":[[-0.462,0.287],[-0.429,-0.437],[-0.908,-0.561],[-0.338,0],[-1.276,0.131],[-1.076,1.151],[0,0],[0.146,1.979],[1.524,1.679],[0,0],[0.228,0.164],[0,0],[0,0],[0,0],[3.746,-2.656],[1.62,-1.805],[0,0],[0,0],[-0.145,-1.793],[-0.937,-1.012],[-0.319,-0.033],[-1.24,0]],"v":[[1.292,-8.986],[-0.003,-7.93],[-1.291,-8.986],[-4.452,-9.807],[-5.443,-9.759],[-8.924,-7.951],[-10.781,-3.445],[-10.784,-2.217],[-8.206,3.254],[-0.617,9.506],[-0.471,9.612],[0.311,9.692],[0.409,9.648],[0.526,9.582],[0.623,9.517],[8.206,3.253],[10.781,-2.158],[10.784,-3.382],[10.781,-3.445],[8.922,-7.953],[5.443,-9.759],[4.452,-9.807]],"c":true},"ix":2},"nm":"heart","mn":"ADBE Vector Shape - Group","hd":false},{"ty":"gf","o":{"a":0,"k":100,"ix":10},"r":1,"g":{"p":3,"k":{"a":0,"k":[0,1,0.376,0.306,0.5,0.967,0.257,0.335,1,0.933,0.137,0.365],"ix":9}},"s":{"a":0,"k":[-0.024,-10.002],"ix":5},"e":{"a":0,"k":[-0.043,9.753],"ix":6},"t":1,"nm":"gradient 1","mn":"ADBE Vector Graphic - G-Fill","hd":false},{"ty":"tr","p":{"a":0,"k":[16,16.269],"ix":2},"a":{"a":0,"k":[0,0],"ix":1},"s":{"a":1,"k":[{"i":{"x":[0.667,0.667],"y":[1,1]},"o":{"x":[0.167,0.167],"y":[0.167,0.167]},"n":["0p667_1_0p167_0p167","0p667_1_0p167_0p167"],"t":1,"s":[0,0],"e":[135,135]},{"i":{"x":[0.667,0.667],"y":[1,1]},"o":{"x":[0.333,0.333],"y":[0,0]},"n":["0p667_1_0p333_0","0p667_1_0p333_0"],"t":9,"s":[135,135],"e":[100,100]},{"t":15}],"ix":3},"r":{"a":0,"k":0,"ix":6},"o":{"a":1,"k":[{"i":{"x":[0.833],"y":[0.833]},"o":{"x":[0.167],"y":[0.167]},"n":["0p833_0p833_0p167_0p167"],"t":1,"s":[50],"e":[100]},{"t":9}],"ix":7},"sk":{"a":0,"k":0,"ix":4},"sa":{"a":0,"k":0,"ix":5},"nm":"变换"}],"nm":"group1","np":2,"cix":2,"ix":1,"mn":"ADBE Vector Group","hd":false}],"ip":1,"op":30,"st":0,"bm":0},{"ddd":0,"ind":2,"ty":4,"nm":"“moment_tool_like_nor”轮廓","sr":1,"ks":{"o":{"a":0,"k":100,"ix":11},"r":{"a":0,"k":0,"ix":10},"p":{"a":0,"k":[28,28,0],"ix":2},"a":{"a":0,"k":[16,16,0],"ix":1},"s":{"a":0,"k":[100,100,100],"ix":6}},"ao":0,"shapes":[{"ty":"gr","it":[{"ind":0,"ty":"sh","ix":1,"ks":{"a":0,"k":{"i":[[0,0],[0.955,1.023],[1.075,0.11],[0.293,0],[0.781,-0.484],[0.489,-0.571],[0.674,0.418],[1.086,0],[0.326,-0.033],[0.826,-0.89],[0.13,-1.616],[0,0],[-1.509,-1.681],[-3.681,-2.617],[0,0],[0,0],[0,0],[-1.455,1.628],[-0.13,1.737]],"o":[[-0.13,-1.616],[-0.815,-0.879],[-0.314,-0.033],[-1.097,0],[-0.674,0.418],[-0.489,-0.56],[-0.781,-0.484],[-0.282,0],[-1.074,0.11],[-0.955,1.023],[0,0],[0.13,1.737],[1.476,1.628],[0,0],[0,0],[0,0],[3.691,-2.617],[1.51,-1.681],[0,0]],"v":[[10,-3.359],[8.35,-7.395],[5.363,-8.956],[4.452,-9],[1.705,-8.296],[0,-6.746],[-1.705,-8.296],[-4.452,-9],[-5.364,-8.956],[-8.35,-7.395],[-10,-3.359],[-10,-2.193],[-7.622,2.754],[-0.163,8.89],[-0.011,9],[0.087,8.956],[0.185,8.89],[7.622,2.754],[10,-2.193]],"c":true},"ix":2},"nm":"路径 1","mn":"ADBE Vector Shape - Group","hd":false},{"ty":"st","c":{"a":0,"k":[1,1,1,1],"ix":3},"o":{"a":0,"k":100,"ix":4},"w":{"a":0,"k":1.5,"ix":5},"lc":2,"lj":2,"nm":"描边 1","mn":"ADBE Vector Graphic - Stroke","hd":false},{"ty":"tr","p":{"a":0,"k":[16,16.246],"ix":2},"a":{"a":0,"k":[0,0],"ix":1},"s":{"a":0,"k":[100,100],"ix":3},"r":{"a":0,"k":0,"ix":6},"o":{"a":0,"k":100,"ix":7},"sk":{"a":0,"k":0,"ix":4},"sa":{"a":0,"k":0,"ix":5},"nm":"变换"}],"nm":"组 1","np":2,"cix":2,"ix":1,"mn":"ADBE Vector Group","hd":false}],"ip":0,"op":5,"st":0,"bm":0},{"ddd":0,"ind":3,"ty":4,"nm":"心7","sr":1,"ks":{"o":{"a":1,"k":[{"i":{"x":[0.833],"y":[0.833]},"o":{"x":[0.167],"y":[0.167]},"n":["0p833_0p833_0p167_0p167"],"t":26,"s":[40],"e":[0]},{"t":30}],"ix":11},"r":{"a":0,"k":0,"ix":10},"p":{"a":1,"k":[{"i":{"x":0.667,"y":1},"o":{"x":0.167,"y":0.167},"n":"0p667_1_0p167_0p167","t":7,"s":[28,28,0],"e":[26.128,42.625,0],"to":[3.60302758216858,10.5437002182007,0],"ti":[2.72250151634216,4.99742412567139,0]},{"i":{"x":0.833,"y":0.833},"o":{"x":0.333,"y":0},"n":"0p833_0p833_0p333_0","t":16,"s":[26.128,42.625,0],"e":[29,4.428,0],"to":[-2.9661111831665,-5.44459390640259,0],"ti":[6.73637723922729,7.55015087127686,0]},{"t":30}],"ix":2},"a":{"a":0,"k":[0,0,0],"ix":1},"s":{"a":0,"k":[100,100,100],"ix":6}},"ao":0,"shapes":[{"ty":"gr","it":[{"ind":0,"ty":"sh","ix":1,"ks":{"a":0,"k":{"i":[[0.91,-0.563],[0.422,-0.428],[0.46,0.286],[1.233,0],[0.329,-0.033],[0.947,-1.021],[0.144,-1.793],[0,0],[-1.62,-1.806],[-3.73,-2.653],[0,0],[-0.256,0.115],[0,0],[0,0],[0,0],[-1.504,1.683],[-0.144,1.92],[0,0],[0,0],[1.078,1.153],[1.272,0.13],[0.349,0]],"o":[[-0.462,0.287],[-0.429,-0.437],[-0.908,-0.561],[-0.338,0],[-1.276,0.131],[-1.076,1.151],[0,0],[0.146,1.979],[1.524,1.679],[0,0],[0.228,0.164],[0,0],[0,0],[0,0],[3.746,-2.656],[1.62,-1.805],[0,0],[0,0],[-0.145,-1.793],[-0.937,-1.012],[-0.319,-0.033],[-1.24,0]],"v":[[1.292,-8.986],[-0.003,-7.93],[-1.291,-8.986],[-4.452,-9.807],[-5.443,-9.759],[-8.924,-7.951],[-10.781,-3.445],[-10.784,-2.217],[-8.206,3.254],[-0.617,9.506],[-0.471,9.612],[0.311,9.692],[0.409,9.648],[0.526,9.582],[0.623,9.517],[8.206,3.253],[10.781,-2.158],[10.784,-3.382],[10.781,-3.445],[8.922,-7.953],[5.443,-9.759],[4.452,-9.807]],"c":true},"ix":2},"nm":"路径 2","mn":"ADBE Vector Shape - Group","hd":false},{"ty":"fl","c":{"a":0,"k":[0.933333337307,0.29411765933,0.29411765933,1],"ix":4},"o":{"a":0,"k":100,"ix":5},"r":1,"nm":"填充 1","mn":"ADBE Vector Graphic - Fill","hd":false},{"ty":"tr","p":{"a":0,"k":[0,0],"ix":2},"a":{"a":0,"k":[0,0],"ix":1},"s":{"a":0,"k":[25,25],"ix":3},"r":{"a":0,"k":0,"ix":6},"o":{"a":0,"k":100,"ix":7},"sk":{"a":0,"k":0,"ix":4},"sa":{"a":0,"k":0,"ix":5},"nm":"变换"}],"nm":"组 1","np":2,"cix":2,"ix":1,"mn":"ADBE Vector Group","hd":false}],"ip":7,"op":30,"st":-5,"bm":0},{"ddd":0,"ind":4,"ty":4,"nm":"心6","sr":1,"ks":{"o":{"a":1,"k":[{"i":{"x":[0.833],"y":[0.833]},"o":{"x":[0.167],"y":[0.167]},"n":["0p833_0p833_0p167_0p167"],"t":26,"s":[40],"e":[0]},{"t":30}],"ix":11},"r":{"a":0,"k":0,"ix":10},"p":{"a":1,"k":[{"i":{"x":0.667,"y":1},"o":{"x":0.167,"y":0.167},"n":"0p667_1_0p167_0p167","t":7,"s":[28,28,0],"e":[13.128,31.625,0],"to":[-3.64697241783142,17.293701171875,0],"ti":[-0.18114750087261,7.30151987075806,0]},{"i":{"x":0.833,"y":0.833},"o":{"x":0.333,"y":0},"n":"0p833_0p833_0p333_0","t":16,"s":[13.128,31.625,0],"e":[5,4.428,0],"to":[0.30469539761543,-12.2813701629639,0],"ti":[6.73637723922729,7.55015087127686,0]},{"t":30}],"ix":2},"a":{"a":0,"k":[0,0,0],"ix":1},"s":{"a":0,"k":[100,100,100],"ix":6}},"ao":0,"shapes":[{"ty":"gr","it":[{"ind":0,"ty":"sh","ix":1,"ks":{"a":0,"k":{"i":[[0.91,-0.563],[0.422,-0.428],[0.46,0.286],[1.233,0],[0.329,-0.033],[0.947,-1.021],[0.144,-1.793],[0,0],[-1.62,-1.806],[-3.73,-2.653],[0,0],[-0.256,0.115],[0,0],[0,0],[0,0],[-1.504,1.683],[-0.144,1.92],[0,0],[0,0],[1.078,1.153],[1.272,0.13],[0.349,0]],"o":[[-0.462,0.287],[-0.429,-0.437],[-0.908,-0.561],[-0.338,0],[-1.276,0.131],[-1.076,1.151],[0,0],[0.146,1.979],[1.524,1.679],[0,0],[0.228,0.164],[0,0],[0,0],[0,0],[3.746,-2.656],[1.62,-1.805],[0,0],[0,0],[-0.145,-1.793],[-0.937,-1.012],[-0.319,-0.033],[-1.24,0]],"v":[[1.292,-8.986],[-0.003,-7.93],[-1.291,-8.986],[-4.452,-9.807],[-5.443,-9.759],[-8.924,-7.951],[-10.781,-3.445],[-10.784,-2.217],[-8.206,3.254],[-0.617,9.506],[-0.471,9.612],[0.311,9.692],[0.409,9.648],[0.526,9.582],[0.623,9.517],[8.206,3.253],[10.781,-2.158],[10.784,-3.382],[10.781,-3.445],[8.922,-7.953],[5.443,-9.759],[4.452,-9.807]],"c":true},"ix":2},"nm":"路径 2","mn":"ADBE Vector Shape - Group","hd":false},{"ty":"fl","c":{"a":0,"k":[0.933333337307,0.29411765933,0.29411765933,1],"ix":4},"o":{"a":0,"k":100,"ix":5},"r":1,"nm":"填充 1","mn":"ADBE Vector Graphic - Fill","hd":false},{"ty":"tr","p":{"a":0,"k":[0,0],"ix":2},"a":{"a":0,"k":[0,0],"ix":1},"s":{"a":0,"k":[25,25],"ix":3},"r":{"a":0,"k":0,"ix":6},"o":{"a":0,"k":100,"ix":7},"sk":{"a":0,"k":0,"ix":4},"sa":{"a":0,"k":0,"ix":5},"nm":"变换"}],"nm":"组 1","np":2,"cix":2,"ix":1,"mn":"ADBE Vector Group","hd":false}],"ip":7,"op":30,"st":-5,"bm":0},{"ddd":0,"ind":5,"ty":4,"nm":"心5","sr":1,"ks":{"o":{"a":1,"k":[{"i":{"x":[0.833],"y":[0.833]},"o":{"x":[0.167],"y":[0.167]},"n":["0p833_0p833_0p167_0p167"],"t":26,"s":[40],"e":[0]},{"t":30}],"ix":11},"r":{"a":0,"k":0,"ix":10},"p":{"a":1,"k":[{"i":{"x":0.667,"y":1},"o":{"x":0.167,"y":0.167},"n":"0p667_1_0p167_0p167","t":7,"s":[28,28,0],"e":[18.128,47.625,0],"to":[2.10302758216858,14.7937002182007,0],"ti":[3.38955783843994,3.77145504951477,0]},{"i":{"x":0.833,"y":0.833},"o":{"x":0.333,"y":0},"n":"0p833_0p833_0p333_0","t":16,"s":[18.128,47.625,0],"e":[7,23.428,0],"to":[-5.63568830490112,-6.27065420150757,0],"ti":[5.98637723922729,4.55015087127686,0]},{"t":30}],"ix":2},"a":{"a":0,"k":[0,0,0],"ix":1},"s":{"a":0,"k":[100,100,100],"ix":6}},"ao":0,"shapes":[{"ty":"gr","it":[{"ind":0,"ty":"sh","ix":1,"ks":{"a":0,"k":{"i":[[0.91,-0.563],[0.422,-0.428],[0.46,0.286],[1.233,0],[0.329,-0.033],[0.947,-1.021],[0.144,-1.793],[0,0],[-1.62,-1.806],[-3.73,-2.653],[0,0],[-0.256,0.115],[0,0],[0,0],[0,0],[-1.504,1.683],[-0.144,1.92],[0,0],[0,0],[1.078,1.153],[1.272,0.13],[0.349,0]],"o":[[-0.462,0.287],[-0.429,-0.437],[-0.908,-0.561],[-0.338,0],[-1.276,0.131],[-1.076,1.151],[0,0],[0.146,1.979],[1.524,1.679],[0,0],[0.228,0.164],[0,0],[0,0],[0,0],[3.746,-2.656],[1.62,-1.805],[0,0],[0,0],[-0.145,-1.793],[-0.937,-1.012],[-0.319,-0.033],[-1.24,0]],"v":[[1.292,-8.986],[-0.003,-7.93],[-1.291,-8.986],[-4.452,-9.807],[-5.443,-9.759],[-8.924,-7.951],[-10.781,-3.445],[-10.784,-2.217],[-8.206,3.254],[-0.617,9.506],[-0.471,9.612],[0.311,9.692],[0.409,9.648],[0.526,9.582],[0.623,9.517],[8.206,3.253],[10.781,-2.158],[10.784,-3.382],[10.781,-3.445],[8.922,-7.953],[5.443,-9.759],[4.452,-9.807]],"c":true},"ix":2},"nm":"路径 2","mn":"ADBE Vector Shape - Group","hd":false},{"ty":"fl","c":{"a":0,"k":[0.933333337307,0.29411765933,0.29411765933,1],"ix":4},"o":{"a":0,"k":100,"ix":5},"r":1,"nm":"填充 1","mn":"ADBE Vector Graphic - Fill","hd":false},{"ty":"tr","p":{"a":0,"k":[0,0],"ix":2},"a":{"a":0,"k":[0,0],"ix":1},"s":{"a":0,"k":[25,25],"ix":3},"r":{"a":0,"k":0,"ix":6},"o":{"a":0,"k":100,"ix":7},"sk":{"a":0,"k":0,"ix":4},"sa":{"a":0,"k":0,"ix":5},"nm":"变换"}],"nm":"组 1","np":2,"cix":2,"ix":1,"mn":"ADBE Vector Group","hd":false}],"ip":7,"op":30,"st":-5,"bm":0},{"ddd":0,"ind":6,"ty":4,"nm":"心4","sr":1,"ks":{"o":{"a":1,"k":[{"i":{"x":[0.833],"y":[0.833]},"o":{"x":[0.167],"y":[0.167]},"n":["0p833_0p833_0p167_0p167"],"t":26,"s":[40],"e":[0]},{"t":30}],"ix":11},"r":{"a":0,"k":0,"ix":10},"p":{"a":1,"k":[{"i":{"x":0.667,"y":1},"o":{"x":0.167,"y":0.167},"n":"0p667_1_0p167_0p167","t":7,"s":[28,28,0],"e":[50.128,46.625,0],"to":[4.85302734375,14.0437002182007,0],"ti":[-5.60763740539551,5.61827898025513,0]},{"i":{"x":0.833,"y":0.833},"o":{"x":0.333,"y":0},"n":"0p833_0p833_0p333_0","t":16,"s":[50.128,46.625,0],"e":[45,14.428,0],"to":[7.0543966293335,-7.06778335571289,0],"ti":[8.48637676239014,8.05015087127686,0]},{"t":30}],"ix":2},"a":{"a":0,"k":[0,0,0],"ix":1},"s":{"a":0,"k":[100,100,100],"ix":6}},"ao":0,"shapes":[{"ty":"gr","it":[{"ind":0,"ty":"sh","ix":1,"ks":{"a":0,"k":{"i":[[0.91,-0.563],[0.422,-0.428],[0.46,0.286],[1.233,0],[0.329,-0.033],[0.947,-1.021],[0.144,-1.793],[0,0],[-1.62,-1.806],[-3.73,-2.653],[0,0],[-0.256,0.115],[0,0],[0,0],[0,0],[-1.504,1.683],[-0.144,1.92],[0,0],[0,0],[1.078,1.153],[1.272,0.13],[0.349,0]],"o":[[-0.462,0.287],[-0.429,-0.437],[-0.908,-0.561],[-0.338,0],[-1.276,0.131],[-1.076,1.151],[0,0],[0.146,1.979],[1.524,1.679],[0,0],[0.228,0.164],[0,0],[0,0],[0,0],[3.746,-2.656],[1.62,-1.805],[0,0],[0,0],[-0.145,-1.793],[-0.937,-1.012],[-0.319,-0.033],[-1.24,0]],"v":[[1.292,-8.986],[-0.003,-7.93],[-1.291,-8.986],[-4.452,-9.807],[-5.443,-9.759],[-8.924,-7.951],[-10.781,-3.445],[-10.784,-2.217],[-8.206,3.254],[-0.617,9.506],[-0.471,9.612],[0.311,9.692],[0.409,9.648],[0.526,9.582],[0.623,9.517],[8.206,3.253],[10.781,-2.158],[10.784,-3.382],[10.781,-3.445],[8.922,-7.953],[5.443,-9.759],[4.452,-9.807]],"c":true},"ix":2},"nm":"路径 2","mn":"ADBE Vector Shape - Group","hd":false},{"ty":"fl","c":{"a":0,"k":[0.933333337307,0.29411765933,0.29411765933,1],"ix":4},"o":{"a":0,"k":100,"ix":5},"r":1,"nm":"填充 1","mn":"ADBE Vector Graphic - Fill","hd":false},{"ty":"tr","p":{"a":0,"k":[0,0],"ix":2},"a":{"a":0,"k":[0,0],"ix":1},"s":{"a":0,"k":[25,25],"ix":3},"r":{"a":0,"k":0,"ix":6},"o":{"a":0,"k":100,"ix":7},"sk":{"a":0,"k":0,"ix":4},"sa":{"a":0,"k":0,"ix":5},"nm":"变换"}],"nm":"组 1","np":2,"cix":2,"ix":1,"mn":"ADBE Vector Group","hd":false}],"ip":7,"op":30,"st":-5,"bm":0},{"ddd":0,"ind":7,"ty":4,"nm":"心3","sr":1,"ks":{"o":{"a":1,"k":[{"i":{"x":[0.833],"y":[0.833]},"o":{"x":[0.167],"y":[0.167]},"n":["0p833_0p833_0p167_0p167"],"t":26,"s":[40],"e":[0]},{"t":30}],"ix":11},"r":{"a":0,"k":0,"ix":10},"p":{"a":1,"k":[{"i":{"x":0.667,"y":1},"o":{"x":0.167,"y":0.167},"n":"0p667_1_0p167_0p167","t":7,"s":[28,28,0],"e":[40.128,48.625,0],"to":[4.85302734375,14.0437002182007,0],"ti":[-7.90744161605835,0.69500201940536,0]},{"i":{"x":0.833,"y":0.833},"o":{"x":0.333,"y":0},"n":"0p833_0p833_0p333_0","t":16,"s":[40.128,48.625,0],"e":[45,21.428,0],"to":[9.3043966293335,-0.81778341531754,0],"ti":[-8.76362323760986,13.5501508712769,0]},{"t":30}],"ix":2},"a":{"a":0,"k":[0,0,0],"ix":1},"s":{"a":0,"k":[100,100,100],"ix":6}},"ao":0,"shapes":[{"ty":"gr","it":[{"ind":0,"ty":"sh","ix":1,"ks":{"a":0,"k":{"i":[[0.91,-0.563],[0.422,-0.428],[0.46,0.286],[1.233,0],[0.329,-0.033],[0.947,-1.021],[0.144,-1.793],[0,0],[-1.62,-1.806],[-3.73,-2.653],[0,0],[-0.256,0.115],[0,0],[0,0],[0,0],[-1.504,1.683],[-0.144,1.92],[0,0],[0,0],[1.078,1.153],[1.272,0.13],[0.349,0]],"o":[[-0.462,0.287],[-0.429,-0.437],[-0.908,-0.561],[-0.338,0],[-1.276,0.131],[-1.076,1.151],[0,0],[0.146,1.979],[1.524,1.679],[0,0],[0.228,0.164],[0,0],[0,0],[0,0],[3.746,-2.656],[1.62,-1.805],[0,0],[0,0],[-0.145,-1.793],[-0.937,-1.012],[-0.319,-0.033],[-1.24,0]],"v":[[1.292,-8.986],[-0.003,-7.93],[-1.291,-8.986],[-4.452,-9.807],[-5.443,-9.759],[-8.924,-7.951],[-10.781,-3.445],[-10.784,-2.217],[-8.206,3.254],[-0.617,9.506],[-0.471,9.612],[0.311,9.692],[0.409,9.648],[0.526,9.582],[0.623,9.517],[8.206,3.253],[10.781,-2.158],[10.784,-3.382],[10.781,-3.445],[8.922,-7.953],[5.443,-9.759],[4.452,-9.807]],"c":true},"ix":2},"nm":"路径 2","mn":"ADBE Vector Shape - Group","hd":false},{"ty":"fl","c":{"a":0,"k":[0.933333337307,0.29411765933,0.29411765933,1],"ix":4},"o":{"a":0,"k":100,"ix":5},"r":1,"nm":"填充 1","mn":"ADBE Vector Graphic - Fill","hd":false},{"ty":"tr","p":{"a":0,"k":[0,0],"ix":2},"a":{"a":0,"k":[0,0],"ix":1},"s":{"a":0,"k":[25,25],"ix":3},"r":{"a":0,"k":0,"ix":6},"o":{"a":0,"k":100,"ix":7},"sk":{"a":0,"k":0,"ix":4},"sa":{"a":0,"k":0,"ix":5},"nm":"变换"}],"nm":"组 1","np":2,"cix":2,"ix":1,"mn":"ADBE Vector Group","hd":false}],"ip":7,"op":30,"st":-5,"bm":0},{"ddd":0,"ind":8,"ty":4,"nm":"心2","sr":1,"ks":{"o":{"a":1,"k":[{"i":{"x":[0.833],"y":[0.833]},"o":{"x":[0.167],"y":[0.167]},"n":["0p833_0p833_0p167_0p167"],"t":26,"s":[40],"e":[0]},{"t":30}],"ix":11},"r":{"a":0,"k":0,"ix":10},"p":{"a":1,"k":[{"i":{"x":0.667,"y":1},"o":{"x":0.167,"y":0.167},"n":"0p667_1_0p167_0p167","t":7,"s":[28,28,0],"e":[48.128,31.625,0],"to":[4.85302734375,14.0437002182007,0],"ti":[1.79182434082031,7.73304748535156,0]},{"i":{"x":0.833,"y":0.833},"o":{"x":0.333,"y":0},"n":"0p833_0p833_0p333_0","t":16,"s":[48.128,31.625,0],"e":[51,4.428,0],"to":[-1.69560348987579,-7.31778335571289,0],"ti":[-6.01362276077271,10.8001508712769,0]},{"t":30}],"ix":2},"a":{"a":0,"k":[0,0,0],"ix":1},"s":{"a":0,"k":[100,100,100],"ix":6}},"ao":0,"shapes":[{"ty":"gr","it":[{"ind":0,"ty":"sh","ix":1,"ks":{"a":0,"k":{"i":[[0.91,-0.563],[0.422,-0.428],[0.46,0.286],[1.233,0],[0.329,-0.033],[0.947,-1.021],[0.144,-1.793],[0,0],[-1.62,-1.806],[-3.73,-2.653],[0,0],[-0.256,0.115],[0,0],[0,0],[0,0],[-1.504,1.683],[-0.144,1.92],[0,0],[0,0],[1.078,1.153],[1.272,0.13],[0.349,0]],"o":[[-0.462,0.287],[-0.429,-0.437],[-0.908,-0.561],[-0.338,0],[-1.276,0.131],[-1.076,1.151],[0,0],[0.146,1.979],[1.524,1.679],[0,0],[0.228,0.164],[0,0],[0,0],[0,0],[3.746,-2.656],[1.62,-1.805],[0,0],[0,0],[-0.145,-1.793],[-0.937,-1.012],[-0.319,-0.033],[-1.24,0]],"v":[[1.292,-8.986],[-0.003,-7.93],[-1.291,-8.986],[-4.452,-9.807],[-5.443,-9.759],[-8.924,-7.951],[-10.781,-3.445],[-10.784,-2.217],[-8.206,3.254],[-0.617,9.506],[-0.471,9.612],[0.311,9.692],[0.409,9.648],[0.526,9.582],[0.623,9.517],[8.206,3.253],[10.781,-2.158],[10.784,-3.382],[10.781,-3.445],[8.922,-7.953],[5.443,-9.759],[4.452,-9.807]],"c":true},"ix":2},"nm":"路径 2","mn":"ADBE Vector Shape - Group","hd":false},{"ty":"fl","c":{"a":0,"k":[0.933333337307,0.29411765933,0.29411765933,1],"ix":4},"o":{"a":0,"k":100,"ix":5},"r":1,"nm":"填充 1","mn":"ADBE Vector Graphic - Fill","hd":false},{"ty":"tr","p":{"a":0,"k":[0,0],"ix":2},"a":{"a":0,"k":[0,0],"ix":1},"s":{"a":0,"k":[25,25],"ix":3},"r":{"a":0,"k":0,"ix":6},"o":{"a":0,"k":100,"ix":7},"sk":{"a":0,"k":0,"ix":4},"sa":{"a":0,"k":0,"ix":5},"nm":"变换"}],"nm":"组 1","np":2,"cix":2,"ix":1,"mn":"ADBE Vector Group","hd":false}],"ip":7,"op":30,"st":-5,"bm":0},{"ddd":0,"ind":9,"ty":4,"nm":"心1","sr":1,"ks":{"o":{"a":1,"k":[{"i":{"x":[0.833],"y":[0.833]},"o":{"x":[0.167],"y":[0.167]},"n":["0p833_0p833_0p167_0p167"],"t":26,"s":[40],"e":[0]},{"t":30}],"ix":11},"r":{"a":0,"k":0,"ix":10},"p":{"a":1,"k":[{"i":{"x":0.667,"y":1},"o":{"x":0.167,"y":0.167},"n":"0p667_1_0p167_0p167","t":7,"s":[28,28,0],"e":[7.128,42.625,0],"to":[-4.14697265625,20.043701171875,0],"ti":[3.09718728065491,6.84342432022095,0]},{"i":{"x":0.833,"y":0.833},"o":{"x":0.333,"y":0},"n":"0p833_0p833_0p333_0","t":16,"s":[7.128,42.625,0],"e":[18,10.428,0],"to":[-4.29182434082031,-9.48304748535156,0],"ti":[1.48637712001801,17.8001499176025,0]},{"t":30}],"ix":2},"a":{"a":0,"k":[0,0,0],"ix":1},"s":{"a":0,"k":[100,100,100],"ix":6}},"ao":0,"shapes":[{"ty":"gr","it":[{"ind":0,"ty":"sh","ix":1,"ks":{"a":0,"k":{"i":[[0.91,-0.563],[0.422,-0.428],[0.46,0.286],[1.233,0],[0.329,-0.033],[0.947,-1.021],[0.144,-1.793],[0,0],[-1.62,-1.806],[-3.73,-2.653],[0,0],[-0.256,0.115],[0,0],[0,0],[0,0],[-1.504,1.683],[-0.144,1.92],[0,0],[0,0],[1.078,1.153],[1.272,0.13],[0.349,0]],"o":[[-0.462,0.287],[-0.429,-0.437],[-0.908,-0.561],[-0.338,0],[-1.276,0.131],[-1.076,1.151],[0,0],[0.146,1.979],[1.524,1.679],[0,0],[0.228,0.164],[0,0],[0,0],[0,0],[3.746,-2.656],[1.62,-1.805],[0,0],[0,0],[-0.145,-1.793],[-0.937,-1.012],[-0.319,-0.033],[-1.24,0]],"v":[[1.292,-8.986],[-0.003,-7.93],[-1.291,-8.986],[-4.452,-9.807],[-5.443,-9.759],[-8.924,-7.951],[-10.781,-3.445],[-10.784,-2.217],[-8.206,3.254],[-0.617,9.506],[-0.471,9.612],[0.311,9.692],[0.409,9.648],[0.526,9.582],[0.623,9.517],[8.206,3.253],[10.781,-2.158],[10.784,-3.382],[10.781,-3.445],[8.922,-7.953],[5.443,-9.759],[4.452,-9.807]],"c":true},"ix":2},"nm":"路径 2","mn":"ADBE Vector Shape - Group","hd":false},{"ty":"fl","c":{"a":0,"k":[0.933333337307,0.29411765933,0.29411765933,1],"ix":4},"o":{"a":0,"k":100,"ix":5},"r":1,"nm":"填充 1","mn":"ADBE Vector Graphic - Fill","hd":false},{"ty":"tr","p":{"a":0,"k":[0,0],"ix":2},"a":{"a":0,"k":[0,0],"ix":1},"s":{"a":0,"k":[25,25],"ix":3},"r":{"a":0,"k":0,"ix":6},"o":{"a":0,"k":100,"ix":7},"sk":{"a":0,"k":0,"ix":4},"sa":{"a":0,"k":0,"ix":5},"nm":"变换"}],"nm":"组 1","np":2,"cix":2,"ix":1,"mn":"ADBE Vector Group","hd":false}],"ip":7,"op":30,"st":-5,"bm":0}],"markers":[]}